{
  "frames": {
    "Untitled-22_0000_Group-61.png_0014_Untitled-22_0015_Group-58.png": {
      "frame": {
        "x": 2,
        "y": 2,
        "w": 345,
        "h": 345
      },
      "rotated": false,
      "trimmed": false,
      "spriteSourceSize": {
        "x": 0,
        "y": 0,
        "w": 345,
        "h": 345
      },
      "sourceSize": {
        "w": 345,
        "h": 345
      },
      "pivot": {
        "x": 0.5,
        "y": 0.5
      }
    },
    "Untitled-23_0009_Untitled-6_0029_Group-52.png": {
      "frame": {
        "x": 2,
        "y": 351,
        "w": 139,
        "h": 122
      },
      "rotated": false,
      "trimmed": false,
      "spriteSourceSize": {
        "x": 0,
        "y": 0,
        "w": 139,
        "h": 122
      },
      "sourceSize": {
        "w": 139,
        "h": 122
      },
      "pivot": {
        "x": 0.5,
        "y": 0.5
      }
    },
    "right-brow.png": {
      "frame": {
        "x": 2,
        "y": 477,
        "w": 76,
        "h": 33
      },
      "rotated": false,
      "trimmed": false,
      "spriteSourceSize": {
        "x": 0,
        "y": 0,
        "w": 76,
        "h": 33
      },
      "sourceSize": {
        "w": 76,
        "h": 33
      },
      "pivot": {
        "x": 0.5,
        "y": 0.5
      }
    },
    "right-lashes.png": {
      "frame": {
        "x": 145,
        "y": 351,
        "w": 110,
        "h": 110
      },
      "rotated": false,
      "trimmed": false,
      "spriteSourceSize": {
        "x": 0,
        "y": 0,
        "w": 110,
        "h": 110
      },
      "sourceSize": {
        "w": 110,
        "h": 110
      },
      "pivot": {
        "x": 0.5,
        "y": 0.5
      }
    },
    "Untitled-23_0022_Untitled-6_0016_Group-102.png": {
      "frame": {
        "x": 259,
        "y": 351,
        "w": 290,
        "h": 108
      },
      "rotated": false,
      "trimmed": false,
      "spriteSourceSize": {
        "x": 0,
        "y": 0,
        "w": 290,
        "h": 108
      },
      "sourceSize": {
        "w": 290,
        "h": 108
      },
      "pivot": {
        "x": 0.5,
        "y": 0.5
      }
    },
    "right-lens.png": {
      "frame": {
        "x": 553,
        "y": 351,
        "w": 75,
        "h": 75
      },
      "rotated": false,
      "trimmed": false,
      "spriteSourceSize": {
        "x": 0,
        "y": 0,
        "w": 75,
        "h": 75
      },
      "sourceSize": {
        "w": 75,
        "h": 75
      },
      "pivot": {
        "x": 0.5,
        "y": 0.5
      }
    },
    "Untitled-24_0002_Untitled-14_0000_sad-copy-6.png": {
      "frame": {
        "x": 553,
        "y": 430,
        "w": 123,
        "h": 69
      },
      "rotated": false,
      "trimmed": false,
      "spriteSourceSize": {
        "x": 0,
        "y": 0,
        "w": 123,
        "h": 69
      },
      "sourceSize": {
        "w": 123,
        "h": 69
      },
      "pivot": {
        "x": 0.5,
        "y": 0.5
      }
    },
    "Untitled-24_0000_Untitled-14_0002_smile-copy-6.png": {
      "frame": {
        "x": 632,
        "y": 351,
        "w": 115,
        "h": 69
      },
      "rotated": false,
      "trimmed": true,
      "spriteSourceSize": {
        "x": 8,
        "y": 0,
        "w": 115,
        "h": 69
      },
      "sourceSize": {
        "w": 123,
        "h": 69
      },
      "pivot": {
        "x": 0.5,
        "y": 0.5
      }
    },
    "Untitled-24_0001_Untitled-14_0001_normal-copy-6.png": {
      "frame": {
        "x": 680,
        "y": 424,
        "w": 115,
        "h": 69
      },
      "rotated": false,
      "trimmed": true,
      "spriteSourceSize": {
        "x": 8,
        "y": 0,
        "w": 115,
        "h": 69
      },
      "sourceSize": {
        "w": 123,
        "h": 69
      },
      "pivot": {
        "x": 0.5,
        "y": 0.5
      }
    },
    "Untitled-4_0000_basic-copy-5.png_0013_Untitled-4_0015_Shape-17-copy-2.png": {
      "frame": {
        "x": 799,
        "y": 2,
        "w": 86,
        "h": 165
      },
      "rotated": false,
      "trimmed": true,
      "spriteSourceSize": {
        "x": 99,
        "y": 53,
        "w": 86,
        "h": 165
      },
      "sourceSize": {
        "w": 185,
        "h": 271
      },
      "pivot": {
        "x": 0.5,
        "y": 0.5
      }
    }
  },
  "meta": {
    "app": "http://free-tex-packer.com",
    "version": "0.6.7",
    "image": "male.png",
    "format": "RGBA8888",
    "size": {
      "w": 1024,
      "h": 512
    },
    "scale": 1
  }
}